monee/__init__.py
monee/express/__init__.py
monee/io/__init__.py
monee/io/from_pandapower.py
monee/io/from_simbench.py
monee/io/matpower.py
monee/io/native.py
monee/model/__init__.py
monee/model/branch.py
monee/model/child.py
monee/model/core.py
monee/model/grid.py
monee/model/multi.py
monee/model/network.py
monee/model/node.py
monee/model/formulation/__init__.py
monee/model/formulation/core.py
monee/model/formulation/el.py
monee/model/formulation/misoc/__init__.py
monee/model/formulation/misoc/el.py
monee/model/formulation/nonlinear/__init__.py
monee/model/formulation/nonlinear/ac.py
monee/model/phys/__init__.py
monee/model/phys/constant.py
monee/model/phys/core/__init__.py
monee/model/phys/core/hydraulics.py
monee/model/phys/linear/__init__.py
monee/model/phys/linear/dc.py
monee/model/phys/misoc/__init__.py
monee/model/phys/misoc/pf.py
monee/model/phys/nonlinear/__init__.py
monee/model/phys/nonlinear/ac.py
monee/model/phys/nonlinear/gf.py
monee/model/phys/nonlinear/hf.py
monee/model/phys/nonlinear/wf.py
monee/network/__init__.py
monee/network/mes.py
monee/network/bench/__init__.py
monee/network/bench/mes_simbench.py
monee/problem/__init__.py
monee/problem/core.py
monee/problem/load_shedding.py
monee/problem/metric.py
monee/simulation/__init__.py
monee/simulation/core.py
monee/simulation/timeseries.py
monee/solver/__init__.py
monee/solver/core.py
monee/solver/gekko.py
monee/solver/pyo.py
monee/visualization/__init__.py
monee/visualization/visualization.py
monee-1.1.0.dist-info/licenses/LICENSE
monee-1.1.0.dist-info/METADATA
monee-1.1.0.dist-info/WHEEL
monee-1.1.0.dist-info/top_level.txt
monee-1.1.0.dist-info/RECORD
