Metadata-Version: 2.4
Name: monee
Version: 1.1.0
Summary: Framework for calculating the steady-state energy flow and for solving optimization problems in coupled energy grids (gas, heat, electricity)
Author-email: Rico Schrage <rico.schrage@uol.de>
License-Expression: MIT
Project-URL: Homepage, https://monee.readthedocs.io
Project-URL: Repository, https://monee.readthedocs.io
Project-URL: Issues, https://github.com/Digitalized-Energy-Systems/monee/issues
Classifier: Programming Language :: Python
Classifier: Programming Language :: Python :: 3
Classifier: Programming Language :: Python :: 3.10
Classifier: Programming Language :: Python :: 3.11
Classifier: Programming Language :: Python :: 3.12
Classifier: Programming Language :: Python :: 3.13
Classifier: Programming Language :: Python :: Implementation :: CPython
Classifier: Programming Language :: Python :: Implementation :: PyPy
Requires-Python: >=3.10
License-File: LICENSE
Requires-Dist: scipy>=1.10.1
Requires-Dist: gekko>=1.0.6
Requires-Dist: networkx>=3.0
Requires-Dist: numpy>=1.26.4
Requires-Dist: pandas>=1.5.3
Requires-Dist: geopy>=2.4.1
Requires-Dist: plotly>=6.3.0
Requires-Dist: pyomo
Provides-Extra: simbench
Requires-Dist: simbench>=1.3.0; extra == "simbench"
Requires-Dist: pandapower>=2.9.0; extra == "simbench"
Provides-Extra: test
Requires-Dist: pytest; extra == "test"
Requires-Dist: pytest-cov; extra == "test"
Requires-Dist: pre-commit; extra == "test"
Provides-Extra: testpp
Requires-Dist: pytest; extra == "testpp"
Requires-Dist: peext; extra == "testpp"
Requires-Dist: simbench; extra == "testpp"
Requires-Dist: pandapower==2.9.0; extra == "testpp"
Requires-Dist: pandapipes==0.6.0; extra == "testpp"
Requires-Dist: numpy==1.26.4; extra == "testpp"
Requires-Dist: pytest-cov; extra == "testpp"
Requires-Dist: pre-commit; extra == "testpp"
Requires-Dist: pandas==1.5.3; extra == "testpp"
Requires-Dist: kaleido; extra == "testpp"
Requires-Dist: pygraphviz; extra == "testpp"
Dynamic: license-file
